LICENSE
README.md
setup.py
opacus_dpcr/__init__.py
opacus_dpcr/dpcrOptimizer.py
opacus_dpcr/dpcr_engine.py
opacus_dpcr/tensorNoiMech.py
opacus_dpcr.egg-info/PKG-INFO
opacus_dpcr.egg-info/SOURCES.txt
opacus_dpcr.egg-info/dependency_links.txt
opacus_dpcr.egg-info/requires.txt
opacus_dpcr.egg-info/top_level.txt