Metadata-Version: 2.1
Name: opacus-dpcr
Version: 0.1.1
Summary: Opacus-DPCR extended by Opacus, Using DPCR to obtain better accuracy...
Home-page: https://github.com/imcjp/Opacus-DPCR
Author: Cai Jianping
Author-email: jpingcai@163.com
License: MIT Licence
Keywords: opacus,dpcr,DPLearning
Platform: any
License-File: LICENSE
